{
    "cartlets": [
        {
            "cartItems": [
                {
                    "id": "7",
                    "productId": "5528bc15e4b081cbd4084a24",
                    "quantity": 1,
                    "shippingTotal": 0.0,
                    "sku": "208631678",
                    "subTotal": 24.99,
                    "taxTotal": 0.0,
                    "total": 24.99,
                    "unitPrice": 24.99,
                    "variant": {
                        "available": true,
                        "color": "Warm Orange",
                        "id": "5528bc15e4b081cbd4084a24",
                        "name": "Women's Tunic - MeronaTM",
                        "onSale": false,
                        "price": 24.99,
                        "priceLabel": "$24.99",
                        "productId": 486322237,
                        "productImageUrl": "https://resources.shopstyle.com/pim/a1/b5/a1b5ff6e35b31178d020476891859807_best.jpg",
                        "retailer": {
                            "id": "3",
                            "name": "Target",
                            "userId": 24975130
                        },
                        "size": {
                            "canonicalSize": {
                                "id": "1169",
                                "name": "XXL (20-22)"
                            },
                            "name": "XXL"
                        },
                        "sku": "208631678"
                    }
                }
            ],
            "retailer": {
                "id": "3",
                "name": "Target",
                "userId": 24975130
            },
            "selectedShippingOption": {
                "id": "1",
                "methodTitle": "Standard $5.00",
                "price": 5.0
            }
        }
    ],
    "shippingAddress": {
        "id" : 123,
        "address1": "1 Test Lane",
        "city": "Walnut Creek",
        "country": "US",
        "email": "johnSmith@popsugar.com",
        "firstName": "John",
        "id": 44000402,
        "lastName": "Smith",
        "phone": "9255556572",
        "postalCode": "94598",
        "state": "CA"
    }
}
